LICENSE
README.md
pyproject.toml
src/package_tree/__init__.py
src/package_tree/tree.py
src/package_tree.egg-info/PKG-INFO
src/package_tree.egg-info/SOURCES.txt
src/package_tree.egg-info/dependency_links.txt
src/package_tree.egg-info/entry_points.txt
src/package_tree.egg-info/requires.txt
src/package_tree.egg-info/top_level.txt