Metadata-Version: 2.4
Name: package-tree
Version: 0.1.0
Summary: Graph of python package dependencies
Author-email: Alain Delplanque <alaindelplanque@mailoo.org>
License: MIT
Project-URL: Homepage, https://github.com/adelplanque/package-tree
Project-URL: Bug Tracker, https://github.com/adelplanque/package-tree/issues
Keywords: graph,dependencies
Classifier: Programming Language :: Python :: 3
Classifier: License :: OSI Approved :: MIT License
Classifier: Operating System :: OS Independent
Requires-Python: >=3.8
License-File: LICENSE
Requires-Dist: packaging
Dynamic: license-file
